v1/__init__.py
v1/countries.py
v1/weather.py
v2/__init__.py
v2/countries.py
v2/weather.py
lab10_python_pip_jpelc-0.0.0.dist-info/METADATA
lab10_python_pip_jpelc-0.0.0.dist-info/WHEEL
lab10_python_pip_jpelc-0.0.0.dist-info/top_level.txt
lab10_python_pip_jpelc-0.0.0.dist-info/RECORD
