Metadata-Version: 2.1
Name: lab10-python-pip-jpelc
Version: 0.0.0
Summary: UNKNOWN
Home-page: UNKNOWN
License: UNKNOWN
Platform: UNKNOWN
Requires-Dist: requests
Requires-Dist: json
